{
  "expressionContainers": [
    {
      "containerState": "done",
      "previouslyChangedExpressionState": "default",
      "expression": {
        "arg": {
          "name": "c",
          "highlightType": "default",
          "topLeftBadgeType": "none",
          "bottomRightBadgeType": "none",
          "type": "variable",
          "argPriorityAgg": [],
          "funcPriorityAgg": [],
          "emphasizePriority": false,
          "bound": false
        },
        "body": {
          "arg": {
            "name": "d",
            "highlightType": "default",
            "topLeftBadgeType": "none",
            "bottomRightBadgeType": "none",
            "type": "variable",
            "argPriorityAgg": [],
            "funcPriorityAgg": [],
            "emphasizePriority": false,
            "bound": false
          },
          "body": {
            "arg": {
              "arg": {
                "arg": {
                  "arg": {
                    "arg": {
                      "arg": {
                        "name": "d",
                        "highlightType": "default",
                        "topLeftBadgeType": "none",
                        "bottomRightBadgeType": "none",
                        "type": "variable",
                        "argPriorityAgg": [
                          1,
                          2,
                          3,
                          4,
                          5,
                          6
                        ],
                        "funcPriorityAgg": [],
                        "emphasizePriority": false,
                        "bound": true
                      },
                      "func": {
                        "name": "c",
                        "highlightType": "default",
                        "topLeftBadgeType": "none",
                        "bottomRightBadgeType": "none",
                        "type": "variable",
                        "argPriorityAgg": [],
                        "funcPriorityAgg": [
                          6
                        ],
                        "emphasizePriority": false,
                        "bound": true
                      },
                      "state": "default",
                      "type": "call",
                      "priority": 6
                    },
                    "func": {
                      "name": "c",
                      "highlightType": "default",
                      "topLeftBadgeType": "none",
                      "bottomRightBadgeType": "none",
                      "type": "variable",
                      "argPriorityAgg": [],
                      "funcPriorityAgg": [
                        5
                      ],
                      "emphasizePriority": false,
                      "bound": true
                    },
                    "state": "default",
                    "type": "call",
                    "priority": 5
                  },
                  "func": {
                    "name": "c",
                    "highlightType": "default",
                    "topLeftBadgeType": "none",
                    "bottomRightBadgeType": "none",
                    "type": "variable",
                    "argPriorityAgg": [],
                    "funcPriorityAgg": [
                      4
                    ],
                    "emphasizePriority": false,
                    "bound": true
                  },
                  "state": "default",
                  "type": "call",
                  "priority": 4
                },
                "func": {
                  "name": "c",
                  "highlightType": "default",
                  "topLeftBadgeType": "none",
                  "bottomRightBadgeType": "none",
                  "type": "variable",
                  "argPriorityAgg": [],
                  "funcPriorityAgg": [
                    3
                  ],
                  "emphasizePriority": false,
                  "bound": true
                },
                "state": "default",
                "type": "call",
                "priority": 3
              },
              "func": {
                "name": "c",
                "highlightType": "default",
                "topLeftBadgeType": "none",
                "bottomRightBadgeType": "none",
                "type": "variable",
                "argPriorityAgg": [],
                "funcPriorityAgg": [
                  2
                ],
                "emphasizePriority": false,
                "bound": true
              },
              "state": "default",
              "type": "call",
              "priority": 2
            },
            "func": {
              "name": "c",
              "highlightType": "default",
              "topLeftBadgeType": "none",
              "bottomRightBadgeType": "none",
              "type": "variable",
              "argPriorityAgg": [],
              "funcPriorityAgg": [
                1
              ],
              "emphasizePriority": false,
              "bound": true
            },
            "state": "default",
            "type": "call",
            "priority": 1
          },
          "type": "function"
        },
        "type": "function"
      }
    }
  ],
  "speed": 1,
  "showOnlyFocused": false,
  "caption": {
    "name": "secretCodeCaption",
    "number": 6,
    "letter": "c"
  },
  "hideControls": true,
  "explanationsVisibility": "hidden",
  "hidePriorities": false,
  "variableSize": "md",
  "containerSize": "xxs",
  "hidePlayButton": false,
  "hideBottomRightBadges": false,
  "skipToTheEnd": false,
  "hideFuncUnboundBadgeOnExplanation": false,
  "highlightOverridesCallArgAndFuncUnboundOnly": false,
  "bottomRightBadgeOverrides": {},
  "highlightOverrides": {},
  "highlightOverrideActiveAfterStart": false,
  "argPriorityAggHighlights": [],
  "funcPriorityAggHighlights": [],
  "highlightFunctions": false,
  "superFastForward": false
}
